LICENSE
MANIFEST.in
README.rst
setup.py
ofblockmeshdicthelper/__init__.py
ofblockmeshdicthelper/version.py
ofblockmeshdicthelper.egg-info/PKG-INFO
ofblockmeshdicthelper.egg-info/SOURCES.txt
ofblockmeshdicthelper.egg-info/dependency_links.txt
ofblockmeshdicthelper.egg-info/requires.txt
ofblockmeshdicthelper.egg-info/top_level.txt