Metadata-Version: 1.1
Name: ofblockmeshdicthelper
Version: 0.1.9
Summary: Helper utilities for OpenFOAM blockMeshDict generation.
Home-page: https://github.com/takaakiaoki/ofblockmeshdicthelper
Author: Takaaki AOKI
Author-email: aoki.takaaki@gmail.com
License: UNKNOWN
Platform: UNKNOWN
Classifier: Programming Language :: Python
Classifier: Programming Language :: Python :: 3.4
Classifier: Programming Language :: Python :: 2.7
Classifier: License :: OSI Approved :: MIT License
Classifier: Development Status :: 4 - Beta
Classifier: Environment :: Other Environment
Classifier: Intended Audience :: Science/Research
Classifier: Operating System :: OS Independent
Classifier: Topic :: Scientific/Engineering :: Physics
